mcp_google_analytics/__init__.py
mcp_google_analytics/server.py
mcp_google_analytics-0.0.2.dist-info/METADATA
mcp_google_analytics-0.0.2.dist-info/WHEEL
mcp_google_analytics-0.0.2.dist-info/entry_points.txt
mcp_google_analytics-0.0.2.dist-info/top_level.txt
mcp_google_analytics-0.0.2.dist-info/RECORD
